README.md
pyqtest.py
setup.py
pyqtest.egg-info/PKG-INFO
pyqtest.egg-info/SOURCES.txt
pyqtest.egg-info/dependency_links.txt
pyqtest.egg-info/requires.txt
pyqtest.egg-info/top_level.txt