Metadata-Version: 2.1
Name: pyqtest
Version: 0.1.3
Summary: Tool for visual testing Qt widgets
Home-page: https://github.com/aleneus/pyqtest
Author: Aleksandr Popov
Author-email: aleneus@gmail.com
License: LGPLv3
Keywords: testing,TDD,gui
Platform: UNKNOWN
Classifier: Development Status :: 3 - Alpha
Classifier: Environment :: X11 Applications :: Qt
Classifier: Intended Audience :: Developers
Classifier: License :: OSI Approved :: GNU Lesser General Public License v3 (LGPLv3)
Classifier: Operating System :: POSIX :: Linux
Classifier: Operating System :: Microsoft :: Windows
Classifier: Programming Language :: Python :: 3
Classifier: Topic :: Scientific/Engineering
